vsui.py
vsui-0.1.0.2.dist-info/WHEEL
vsui-0.1.0.2.dist-info/METADATA
vsui-0.1.0.2.dist-info/RECORD
